MANIFEST.in
README-pypi.text
README.md
setup.py
ja2mqtt/__init__.py
ja2mqtt/__main__.py
ja2mqtt/config.py
ja2mqtt/json2table.py
ja2mqtt/utils.py
ja2mqtt.egg-info/PKG-INFO
ja2mqtt.egg-info/SOURCES.txt
ja2mqtt.egg-info/dependency_links.txt
ja2mqtt.egg-info/entry_points.txt
ja2mqtt.egg-info/requires.txt
ja2mqtt.egg-info/top_level.txt
ja2mqtt/commands/__init__.py
ja2mqtt/commands/config.py
ja2mqtt/commands/ja2mqtt.py
ja2mqtt/commands/query.py
ja2mqtt/commands/run.py
ja2mqtt/components/__init__.py
ja2mqtt/components/bridge.py
ja2mqtt/components/mqtt.py
ja2mqtt/components/serial.py
ja2mqtt/components/simulator.py
ja2mqtt/schemas/config-schema.yaml
ja2mqtt/schemas/ja2mqtt-schema.yaml