Metadata-Version: 1.2
Name: ja2mqtt
Version: 1.0.6
Summary: Jablotron MQTT bridge
Home-page: UNKNOWN
Author: Tomas Vitvar
Author-email: tomas@vitvar.com
License: UNKNOWN
Platform: UNKNOWN
Classifier: Development Status :: 5 - Production/Stable
Classifier: Environment :: Console
Classifier: Intended Audience :: Developers
Classifier: Programming Language :: Python :: 3.7
Requires-Python: >=3.6.0
